mcp_oauth2/__init__.py
mcp_oauth2/base.py
mcp_oauth2/tools.py
mcp_oauth2/providers/__init__.py
mcp_oauth2/providers/generic.py
mcp_oauth2/providers/google.py
mcp_oauth2/providers/microsoft.py
teams_mcp/__init__.py
teams_mcp/__main__.py
teams_mcp/api.py
teams_mcp/config.py
teams_mcp/server.py
teams_mcp/api/__init__.py
teams_mcp/api/client.py
teams_mcp/api/rate_limiter.py
teams_mcp/tools/__init__.py
teams_mcp/tools/create_chat.py
teams_mcp/tools/get_messages.py
teams_mcp/tools/list_chats.py
teams_mcp/tools/send_message.py
teams_mcp_python-0.2.1.dist-info/METADATA
teams_mcp_python-0.2.1.dist-info/WHEEL
teams_mcp_python-0.2.1.dist-info/entry_points.txt
teams_mcp_python-0.2.1.dist-info/licenses/LICENSE
teams_mcp_python-0.2.1.dist-info/RECORD
